dialectus/__init__.py
dialectus_cli-0.3.0.dist-info/licenses/LICENSE
dialectus_cli-0.3.0.dist-info/METADATA
dialectus_cli-0.3.0.dist-info/WHEEL
dialectus_cli-0.3.0.dist-info/entry_points.txt
dialectus_cli-0.3.0.dist-info/top_level.txt
dialectus_cli-0.3.0.dist-info/RECORD
