Metadata-Version: 2.4
Name: dialectus-cli
Version: 0.3.0
Summary: Command-line interface for the Dialectus AI debate system
Author: Dialectus AI
License-Expression: MIT
Project-URL: Homepage, https://github.com/Dialectus-AI/dialectus-cli
Project-URL: Repository, https://github.com/Dialectus-AI/dialectus-cli
Project-URL: Issues, https://github.com/Dialectus-AI/dialectus-cli/issues
Keywords: ai,debate,cli,artificial-intelligence
Classifier: Development Status :: 4 - Beta
Classifier: Intended Audience :: Developers
Classifier: Intended Audience :: Education
Classifier: Programming Language :: Python :: 3
Classifier: Programming Language :: Python :: 3.12
Classifier: Programming Language :: Python :: 3.13
Classifier: Programming Language :: Python :: 3.14
Classifier: Topic :: Scientific/Engineering :: Artificial Intelligence
Classifier: Environment :: Console
Requires-Python: >=3.12
License-File: LICENSE
Requires-Dist: rich>=14.1.0
Requires-Dist: click>=8.2.1
Requires-Dist: pydantic>=2.11.0
Requires-Dist: dialectus-engine>=0.4.0
Provides-Extra: dev
Requires-Dist: pyright>=1.1.406; extra == "dev"
Requires-Dist: ruff>=0.5.0; extra == "dev"
Requires-Dist: pytest>=7.0; extra == "dev"
Requires-Dist: pytest-asyncio>=0.23.0; extra == "dev"
Requires-Dist: twine; extra == "dev"
Requires-Dist: build; extra == "dev"
Dynamic: license-file
